metadate_renamer/__init__.py
metadate_renamer/__main__.py
metadate_renamer/extract_date.py
metadate_renamer/rename_worker.py
metadate_renamer/window.py
metadate_renamer-0.2.0.dist-info/WHEEL
metadate_renamer-0.2.0.dist-info/entry_points.txt
metadate_renamer-0.2.0.dist-info/METADATA
metadate_renamer-0.2.0.dist-info/RECORD
